README.md
lznt1.py
setup.py
lznt1.egg-info/PKG-INFO
lznt1.egg-info/SOURCES.txt
lznt1.egg-info/dependency_links.txt
lznt1.egg-info/top_level.txt